{
  "content": "Quantum machine learning (QML) has seen significant advances in recent months, with several breakthrough developments in both theoretical foundations and practical implementations.\n\n## Recent Breakthroughs\n\n**1. Quantum Neural Networks (QNNs)**\nRecent research has demonstrated improved training algorithms for quantum neural networks, with papers showing up to 40% better convergence rates compared to classical approaches. The key innovation involves novel parameter initialization strategies that leverage quantum entanglement properties.\n\n**2. Quantum Variational Algorithms**\nNew variational quantum eigensolver (VQE) implementations have achieved better accuracy in molecular simulation tasks, with some studies reporting results within chemical accuracy for small molecules. This represents a significant step toward practical quantum chemistry applications.\n\n**3. Quantum-Classical Hybrid Systems**\nSeveral research groups have published work on hybrid quantum-classical machine learning systems that can leverage both quantum and classical computational resources efficiently. These systems show promise for near-term quantum advantage in specific optimization problems.\n\n**4. Error Mitigation Techniques**\nNovel error mitigation strategies have been developed that can significantly improve the performance of quantum machine learning algorithms on noisy intermediate-scale quantum (NISQ) devices. These techniques are crucial for practical deployment.\n\n## Current Challenges\n\nDespite these advances, several challenges remain:\n- **Scalability**: Current quantum machine learning algorithms are limited to small problem sizes\n- **Noise Sensitivity**: Quantum algorithms are highly sensitive to environmental noise\n- **Hardware Limitations**: Current quantum computers have limited qubit counts and connectivity\n- **Theoretical Understanding**: The theoretical foundations of quantum machine learning are still being developed\n\n## Future Directions\n\nResearch is moving toward:\n- Larger-scale quantum machine learning algorithms\n- Better error correction and mitigation techniques\n- Quantum advantage demonstrations in real-world applications\n- Improved quantum-classical hybrid architectures\n\n### ðŸ’¡ Related Questions\nâ€¢ What are the current limitations of quantum machine learning hardware?\nâ€¢ How do quantum machine learning algorithms compare to classical deep learning?\nâ€¢ What are the most promising applications for quantum machine learning?\nâ€¢ How can quantum error correction be improved for machine learning tasks?\nâ€¢ What role will quantum machine learning play in drug discovery?\n\n### ðŸ“š Sources\n*ðŸ“– Academic sources prioritized*\n*Searched only: arxiv.org, ieee.org, nature.com, science.org, pubmed.ncbi.nlm.nih.gov*\n\nâ€¢ [Quantum Machine Learning: A Review](https://arxiv.org/abs/2401.12345)\nâ€¢ [Variational Quantum Algorithms for Machine Learning](https://ieee.org/quantum-ml-2024)\nâ€¢ [Quantum Neural Networks: Recent Advances](https://nature.com/articles/quantum-nn-2024)\nâ€¢ [Error Mitigation in Quantum Machine Learning](https://science.org/quantum-error-mitigation)\nâ€¢ [Hybrid Quantum-Classical Machine Learning Systems](https://pubmed.ncbi.nlm.nih.gov/quantum-hybrid-2024)",
  "metadata": {
    "model": "sonar-pro",
    "search_mode": "academic",
    "citations": [
      {
        "url": "https://arxiv.org/abs/2401.12345",
        "title": "Quantum Machine Learning: A Review"
      },
      {
        "url": "https://ieee.org/quantum-ml-2024",
        "title": "Variational Quantum Algorithms for Machine Learning"
      },
      {
        "url": "https://nature.com/articles/quantum-nn-2024",
        "title": "Quantum Neural Networks: Recent Advances"
      },
      {
        "url": "https://science.org/quantum-error-mitigation",
        "title": "Error Mitigation in Quantum Machine Learning"
      },
      {
        "url": "https://pubmed.ncbi.nlm.nih.gov/quantum-hybrid-2024",
        "title": "Hybrid Quantum-Classical Machine Learning Systems"
      }
    ],
    "domain_filter": ["arxiv.org", "ieee.org", "nature.com", "science.org", "pubmed.ncbi.nlm.nih.gov"],
    "recency_filter": "month",
    "images": [],
    "usage": {
      "prompt_tokens": 150,
      "completion_tokens": 800,
      "total_tokens": 950
    },
    "id": "chatcmpl-abc123def456",
    "related_questions": [
      "What are the current limitations of quantum machine learning hardware?",
      "How do quantum machine learning algorithms compare to classical deep learning?",
      "What are the most promising applications for quantum machine learning?",
      "How can quantum error correction be improved for machine learning tasks?",
      "What role will quantum machine learning play in drug discovery?"
    ]
  }
}
